illumio_pylo/AgentStore.py
illumio_pylo/Exception.py
illumio_pylo/IPList.py
illumio_pylo/IPMap.py
illumio_pylo/Label.py
illumio_pylo/LabelCommon.py
illumio_pylo/LabelGroup.py
illumio_pylo/LabelStore.py
illumio_pylo/LabeledObject.py
illumio_pylo/Organization.py
illumio_pylo/Query.py
illumio_pylo/ReferenceTracker.py
illumio_pylo/Rule.py
illumio_pylo/Ruleset.py
illumio_pylo/RulesetStore.py
illumio_pylo/SecurityPrincipal.py
illumio_pylo/Service.py
illumio_pylo/SoftwareVersion.py
illumio_pylo/VirtualService.py
illumio_pylo/VirtualServiceStore.py
illumio_pylo/Workload.py
illumio_pylo/WorkloadStore.py
illumio_pylo/WorkloadStoreSubClasses.py
illumio_pylo/__init__.py
illumio_pylo/tmp.py
illumio_pylo/API/APIConnector.py
illumio_pylo/API/AuditLog.py
illumio_pylo/API/ClusterHealth.py
illumio_pylo/API/CredentialsManager.py
illumio_pylo/API/Explorer.py
illumio_pylo/API/JsonPayloadTypes.py
illumio_pylo/API/RuleSearchQuery.py
illumio_pylo/API/__init__.py
illumio_pylo/Helpers/__init__.py
illumio_pylo/Helpers/exports.py
illumio_pylo/Helpers/functions.py
illumio_pylo/cli/NativeParsers.py
illumio_pylo/cli/__init__.py
illumio_pylo/cli/__main__.py
illumio_pylo/cli/commands/__init__.py
illumio_pylo/cli/commands/credential_manager.py
illumio_pylo/cli/commands/iplist_analyzer.py
illumio_pylo/cli/commands/iplist_import_from_file.py
illumio_pylo/cli/commands/label_delete_unused.py
illumio_pylo/cli/commands/ruleset_export.py
illumio_pylo/cli/commands/update_pce_objects_cache.py
illumio_pylo/cli/commands/ven_compatibility_report_export.py
illumio_pylo/cli/commands/ven_duplicate_remover.py
illumio_pylo/cli/commands/ven_idle_to_visibility.py
illumio_pylo/cli/commands/ven_upgrader.py
illumio_pylo/cli/commands/workload_export.py
illumio_pylo/cli/commands/workload_import.py
illumio_pylo/cli/commands/workload_reset_names_to_null.py
illumio_pylo/cli/commands/workload_update.py
illumio_pylo/cli/commands/workload_used_in_rule_finder.py
illumio_pylo/cli/commands/utils/LabelCreation.py
illumio_pylo-0.3.11.dist-info/licenses/LICENSE
illumio_pylo-0.3.11.dist-info/METADATA
illumio_pylo-0.3.11.dist-info/WHEEL
illumio_pylo-0.3.11.dist-info/top_level.txt
illumio_pylo-0.3.11.dist-info/RECORD
