Metadata-Version: 2.4
Name: illumio_pylo
Version: 0.3.11
Summary: A set of tools and library for working with Illumio PCE
Home-page: https://github.com/cpainchaud/pylo
Author: Christophe Painchaud
Author-email: shellescape@gmail.com
License:                                  Apache License
Project-URL: Homepage, https://github.com/cpainchaud/pylo
Project-URL: Issues, https://github.com/cpainchaud/pylo/issues
Requires-Python: >=3.11
License-File: LICENSE
Requires-Dist: click==8.1.7
Requires-Dist: colorama~=0.4.4
Requires-Dist: cryptography==44.0.1
Requires-Dist: openpyxl~=3.1.3
Requires-Dist: paramiko~=3.4.0
Requires-Dist: prettytable~=3.10.0
Requires-Dist: requests~=2.32.0
Requires-Dist: xlsxwriter~=3.2.0
Dynamic: author
Dynamic: author-email
Dynamic: description
Dynamic: home-page
Dynamic: license-file
Dynamic: requires-python
